prob_distribution
