Metadata-Version: 1.0
Name: prob-distribution
Version: 0.2
Summary: Probability distributions
Home-page: UNKNOWN
Author: UNKNOWN
Author-email: UNKNOWN
License: UNKNOWN
Platform: UNKNOWN
